file_writer_MS/__init__.py
file_writer_MS/file_writer_MS.py
file_writer_MS-0.0.1.dist-info/METADATA
file_writer_MS-0.0.1.dist-info/WHEEL
file_writer_MS-0.0.1.dist-info/top_level.txt
file_writer_MS-0.0.1.dist-info/RECORD
